{
    "nodes": [
      {
        "id": "0",
        "name": "Aomo Ang",
        "symbolSize": 4,
        "x": -260,
        "y": -280,
        "value": "gods/Buddhas",
        "category": 1
      },
      {
        "id": "1",
        "name": "Prince Aomo Ang",
        "symbolSize": 4,
        "x": -250,
        "y": -280,
        "value": "gods/Buddhas",
        "category": 1
      },
      {
        "id": "2",
        "name": "Ao Run",
        "symbolSize": 4,
        "x": -250,
        "y": -270,
        "value": "gods/Buddhas",
        "category": 1
      },
      {
        "id": "3",
        "name": "White Dragon Horse",
        "symbolSize": 32,
        "x": -250,
        "y": -270,
        "value": "Tang Monk's team",
        "category": 0
      },
      {
        "id": "4",
        "name": "White Deer",
        "symbolSize": 4,
        "x": -250,
        "y": -270,
        "value": "monsters",
        "category": 3
      },
      {
        "id": "5",
        "name": "White Elephant",
        "symbolSize": 4,
        "x": -250,
        "y": -270,
        "value": "monsters",
        "category": 3
      },
      {
        "id": "6",
        "name": "Hundred Eyed Demon",
        "symbolSize": 4,
        "x": -250,
        "y": -270,
        "value": "monsters",
        "category": 3
      },
      {
        "id": "7",
        "name": "Chang'e",
        "symbolSize": 8,
        "x": -250,
        "y": -270,
        "value": "gods/Buddhas",
        "category": 1
      },
      {
        "id": "8",
        "name": "Chen Guangrui",
        "symbolSize": 4,
        "x": -250,
        "y": -270,
        "value": "humans",
        "category": 2
      },
      {
        "id": "9",
        "name": "Dapeng Golden Winged Eagle",
        "symbolSize": 4,
        "x": -250,
        "y": -270,
        "value": "monsters",
        "category": 3
      },
      {
        "id": "10",
        "name": "Donglai Buddha Laughing Monk",
        "symbolSize": 4,
        "x": -250,
        "y": -270,
        "value": "gods/Buddhas",
        "category": 1
      },
      {
        "id": "11",
        "name": "Unicorn King",
        "symbolSize": 4,
        "x": -250,
        "y": -270,
        "value": "monsters",
        "category": 3
      },
      {
        "id": "12",
        "name": "24 Dharma Protectors",
        "symbolSize": 4,
        "x": -250,
        "y": -270,
        "value": "gods/Buddhas",
        "category": 1
      },
      {
        "id": "13",
        "name": "Monk Faming",
        "symbolSize": 4,
        "x": -250,
        "y": -270,
        "value": "humans",
        "category": 2
      },
      {
        "id": "14",
        "name": "Gao Cuilan",
        "symbolSize": 16,
        "x": -250,
        "y": -270,
        "value": "humans",
        "category": 2
      },
      {
        "id": "15",
        "name": "Gao Taigong",
        "symbolSize": 4,
        "x": -250,
        "y": -270,
        "value": "humans",
        "category": 2
      },
      {
        "id": "16",
        "name": "Gao Xianglan",
        "symbolSize": 8,
        "x": -250,
        "y": -270,
        "value": "humans",
        "category": 2
      },
      {
        "id": "17",
        "name": "Gao Yulan",
        "symbolSize": 8,
        "x": -250,
        "y": -270,
        "value": "humans",
        "category": 2
      },
      {
        "id": "18",
        "name": "Guanyin",
        "symbolSize": 36,
        "x": -250,
        "y": -270,
        "value": "gods/Buddhas",
        "category": 1
      },
      {
        "id": "19",
        "name": "Black Wind Monster",
        "symbolSize": 4,
        "x": -250,
        "y": -270,
        "value": "monsters",
        "category": 3
      },
      {
        "id": "20",
        "name": "Red Boy",
        "symbolSize": 8,
        "x": -250,
        "y": -270,
        "value": "monsters",
        "category": 3
      },
      {
        "id": "21",
        "name": "Hou Yi",
        "symbolSize": 4,
        "x": -250,
        "y": -270,
        "value": "gods/Buddhas",
        "category": 1
      },
      {
        "id": "22",
        "name": "Hu Aqi",
        "symbolSize": 8,
        "x": -250,
        "y": -270,
        "value": "monsters",
        "category": 3
      },
      {
        "id": "23",
        "name": "Yellow Wind Monster",
        "symbolSize": 4,
        "x": -250,
        "y": -270,
        "value": "monsters",
        "category": 3
      },
      {
        "id": "24",
        "name": "Yellow Marten",
        "symbolSize": 4,
        "x": -250,
        "y": -270,
        "value": "monsters",
        "category": 3
      },
      {
        "id": "25",
        "name": "Yellow Eyebrow Monster",
        "symbolSize": 4,
        "x": -250,
        "y": -270,
        "value": "monsters",
        "category": 3
      },
      {
        "id": "26",
        "name": "Jiao Demon",
        "symbolSize": 4,
        "x": -250,
        "y": -270,
        "value": "monsters",
        "category": 3
      },
      {
        "id": "27",
        "name": "Tang Priest",
        "symbolSize": 4,
        "x": -250,
        "y": -270,
        "value": "gods/Buddhas",
        "category": 1
      },
      {
        "id": "28",
        "name": "Golden Horn",
        "symbolSize": 12,
        "x": -250,
        "y": -270,
        "value": "monsters",
        "category": 3
      },
      {
        "id": "29",
        "name": "Golden Retriever Monster",
        "symbolSize": 4,
        "x": -250,
        "y": -270,
        "value": "monsters",
        "category": 3
      },
      {
        "id": "30",
        "name": "Jinzha",
        "symbolSize": 8,
        "x": -250,
        "y": -270,
        "value": "gods/Buddhas",
        "category": 1
      },
      {
        "id": "31",
        "name": "Nine Headed Lion",
        "symbolSize": 4,
        "x": -250,
        "y": -270,
        "value": "monsters",
        "category": 3
      },
      {
        "id": "32",
        "name": "Nine Tailed Fox",
        "symbolSize": 8,
        "x": -250,
        "y": -270,
        "value": "monsters",
        "category": 3
      },
      {
        "id": "33",
        "name": "Rolling Shutter General",
        "symbolSize": 4,
        "x": -250,
        "y": -270,
        "value": "gods/Buddhas",
        "category": 1
      },
      {
        "id": "34",
        "name": "Kou Dong",
        "symbolSize": 4,
        "x": -250,
        "y": -270,
        "value": "humans",
        "category": 2
      },
      {
        "id": "35",
        "name": "Kou Liang",
        "symbolSize": 8,
        "x": -250,
        "y": -270,
        "value": "humans",
        "category": 2
      },
      {
        "id": "36",
        "name": "Li Jing",
        "symbolSize": 12,
        "x": -250,
        "y": -270,
        "value": "gods/Buddhas",
        "category": 1
      },
      {
        "id": "37",
        "name": "Kou Hong",
        "symbolSize": 4,
        "x": -250,
        "y": -270,
        "value": "humans",
        "category": 2
      },
      {
        "id": "38",
        "name": "Li Shimin",
        "symbolSize": 8,
        "x": -250,
        "y": -270,
        "value": "humans",
        "category": 2
      },
      {
        "id": "39",
        "name": "Li Yuan",
        "symbolSize": 4,
        "x": -250,
        "y": -270,
        "value": "humans",
        "category": 2
      },
      {
        "id": "40",
        "name": "Inspiration Monster",
        "symbolSize": 4,
        "x": -250,
        "y": -270,
        "value": "monsters",
        "category": 3
      },
      {
        "id": "41",
        "name": "Lingji Bodhisattva",
        "symbolSize": 8,
        "x": -250,
        "y": -270,
        "value": "gods/Buddhas",
        "category": 1
      },
      {
        "id": "42",
        "name": "Luan Erjie",
        "symbolSize": 4,
        "x": -250,
        "y": -270,
        "value": "monsters",
        "category": 3
      },
      {
        "id": "43",
        "name": "Subaru Star Official",
        "symbolSize": 4,
        "x": -250,
        "y": -270,
        "value": "gods/Buddhas",
        "category": 1
      },
      {
        "id": "44",
        "name": "Maitreya Buddha",
        "symbolSize": 4,
        "x": -250,
        "y": -270,
        "value": "gods/Buddhas",
        "category": 1
      },
      {
        "id": "45",
        "name": "Macaque Monster",
        "symbolSize": 4,
        "x": -250,
        "y": -270,
        "value": "monsters",
        "category": 3
      },
      {
        "id": "46",
        "name": "Muzha",
        "symbolSize": 8,
        "x": -250,
        "y": -270,
        "value": "gods/Buddhas",
        "category": 1
      },
      {
        "id": "47",
        "name": "Nezha",
        "symbolSize": 12,
        "x": -250,
        "y": -270,
        "value": "gods/Buddhas",
        "category": 1
      },
      {
        "id": "48",
        "name": "Antarctic Longevity Star",
        "symbolSize": 4,
        "x": -250,
        "y": -270,
        "value": "gods/Buddhas",
        "category": 1
      },
      {
        "id": "49",
        "name": "Ox Demon King",
        "symbolSize": 20,
        "x": -250,
        "y": -270,
        "value": "monsters",
        "category": 3
      },
      {
        "id": "50",
        "name": "Peng Demon King",
        "symbolSize": 4,
        "x": -250,
        "y": -270,
        "value": "monsters",
        "category": 3
      },
      {
        "id": "51",
        "name": "Holding Pearl Dragon Maiden",
        "symbolSize": 4,
        "x": -250,
        "y": -270,
        "value": "gods/Buddhas",
        "category": 1
      },
      {
        "id": "52",
        "name": "Vairocana Bodhisattva",
        "symbolSize": 8,
        "x": -250,
        "y": -270,
        "value": "gods/Buddhas",
        "category": 1
      },
      {
        "id": "53",
        "name": "Bodhi Patriarch",
        "symbolSize": 4,
        "x": -250,
        "y": -270,
        "value": "gods/Buddhas",
        "category": 1
      },
      {
        "id": "54",
        "name": "Samantabhadra Bodhisattva",
        "symbolSize": 4,
        "x": -250,
        "y": -270,
        "value": "gods/Buddhas",
        "category": 1
      },
      {
        "id": "55",
        "name": "Green Lion",
        "symbolSize": 4,
        "x": -250,
        "y": -270,
        "value": "monsters",
        "category": 3
      },
      {
        "id": "56",
        "name": "Buddha",
        "symbolSize": 12,
        "x": -250,
        "y": -270,
        "value": "gods/Buddhas",
        "category": 1
      },
      {
        "id": "57",
        "name": "Sha Monk",
        "symbolSize": 20,
        "x": -250,
        "y": -270,
        "value": "Tang Monk's team",
        "category": 0
      },
      {
        "id": "58",
        "name": "Shancai boy",
        "symbolSize": 4,
        "x": -250,
        "y": -270,
        "value": "gods/Buddhas",
        "category": 1
      },
      {
        "id": "59",
        "name": "Lion Camel Monster",
        "symbolSize": 4,
        "x": -250,
        "y": -270,
        "value": "monsters",
        "category": 3
      },
      {
        "id": "60",
        "name": "Mountain Guarding Monster",
        "symbolSize": 4,
        "x": -250,
        "y": -270,
        "value": "monsters",
        "category": 3
      },
      {
        "id": "61",
        "name": "Sun Wukong",
        "symbolSize": 48,
        "x": -250,
        "y": -270,
        "value": "Tang Monk's team",
        "category": 0
      },
      {
        "id": "62",
        "name": "Lord Lao Zi",
        "symbolSize": 12,
        "x": -250,
        "y": -270,
        "value": "gods/Buddhas",
        "category": 1
      },
      {
        "id": "63",
        "name": "Heavenly Lord of Taiyi",
        "symbolSize": 4,
        "x": -250,
        "y": -270,
        "value": "gods/Buddhas",
        "category": 1
      },
      {
        "id": "64",
        "name": "Tang Monk",
        "symbolSize": 36,
        "x": -250,
        "y": -270,
        "value": "Tang Monk's team",
        "category": 0
      },
      {
        "id": "65",
        "name": "Marshal Tianpeng",
        "symbolSize": 4,
        "x": -250,
        "y": -270,
        "value": "gods/Buddhas",
        "category": 1
      },
      {
        "id": "66",
        "name": "Iron Fan Princess",
        "symbolSize": 8,
        "x": -250,
        "y": -270,
        "value": "monsters",
        "category": 3
      },
      {
        "id": "67",
        "name": "Tuolong Monster",
        "symbolSize": 4,
        "x": -250,
        "y": -270,
        "value": "monsters",
        "category": 3
      },
      {
        "id": "68",
        "name": "Bodhisattva Manjusri",
        "symbolSize": 4,
        "x": -250,
        "y": -270,
        "value": "gods/Buddhas",
        "category": 1
      },
      {
        "id": "69",
        "name": "West Sea Dragon Mother",
        "symbolSize": 4,
        "x": -250,
        "y": -270,
        "value": "gods/Buddhas",
        "category": 1
      },
      {
        "id": "70",
        "name": "West Sea Dragon Maiden",
        "symbolSize": 4,
        "x": -250,
        "y": -270,
        "value": "gods/Buddhas",
        "category": 1
      },
      {
        "id": "71",
        "name": "West Sea Dragon King",
        "symbolSize": 4,
        "x": -250,
        "y": -270,
        "value": "gods/Buddhas",
        "category": 1
      },
      {
        "id": "72",
        "name": "West Sea Dragon Prince",
        "symbolSize": 4,
        "x": -250,
        "y": -270,
        "value": "gods/Buddhas",
        "category": 1
      },
      {
        "id": "73",
        "name": "Yin Kaishan",
        "symbolSize": 4,
        "x": -250,
        "y": -270,
        "value": "humans",
        "category": 2
      },
      {
        "id": "74",
        "name": "Yin Wenjiao",
        "symbolSize": 8,
        "x": -250,
        "y": -270,
        "value": "humans",
        "category": 2
      },
      {
        "id": "75",
        "name": "Silver Horn",
        "symbolSize": 12,
        "x": -250,
        "y": -270,
        "value": "monsters",
        "category": 3
      },
      {
        "id": "76",
        "name": "Yuzheng Monster",
        "symbolSize": 4,
        "x": -250,
        "y": -270,
        "value": "monsters",
        "category": 3
      },
      {
        "id": "77",
        "name": "Princess Yumian",
        "symbolSize": 4,
        "x": -250,
        "y": -270,
        "value": "monsters",
        "category": 3
      },
      {
        "id": "78",
        "name": "Jade Rabbit Demon",
        "symbolSize": 4,
        "x": -250,
        "y": -270,
        "value": "monsters",
        "category": 3
      },
      {
        "id": "79",
        "name": "Yuan Shoucheng",
        "symbolSize": 4,
        "x": -250,
        "y": -270,
        "value": "humans",
        "category": 2
      },
      {
        "id": "80",
        "name": "Yuan Tiangang",
        "symbolSize": 4,
        "x": -250,
        "y": -270,
        "value": "humans",
        "category": 2
      },
      {
        "id": "81",
        "name": "Zhenyuanzi",
        "symbolSize": 4,
        "x": -250,
        "y": -270,
        "value": "gods/Buddhas",
        "category": 1
      },
      {
        "id": "82",
        "name": "Zhengyuanlong",
        "symbolSize": 4,
        "x": -250,
        "y": -270,
        "value": "gods/Buddhas",
        "category": 1
      },
      {
        "id": "83",
        "name": "Pigsy",
        "symbolSize": 20,
        "x": -250,
        "y": -270,
        "value": "Tang Monk's team",
        "category": 0
      }
    ],
    "links": [
{"source":"0","target":"2"},
{"source":"1","target":"3"},
{"source":"2","target":"0"},
{"source":"3","target":"64"},
{"source":"3","target":"61"},
{"source":"3","target":"83"},
{"source":"3","target":"57"},
{"source":"3","target":"1"},
{"source":"3","target":"69"},
{"source":"3","target":"70"},
{"source":"3","target":"71"},
{"source":"4","target":"48"},
{"source":"5","target":"54"},
{"source":"6","target":"52"},
{"source":"7","target":"21"},
{"source":"7","target":"78"},
{"source":"8","target":"64"},
{"source":"9","target":"56"},
{"source":"10","target":"25"},
{"source":"11","target":"62"},
{"source":"12","target":"18"},
{"source":"13","target":"64"},
{"source":"14","target":"15"},
{"source":"14","target":"16"},
{"source":"14","target":"17"},
{"source":"14","target":"83"},
{"source":"15","target":"14"},
{"source":"16","target":"14"},
{"source":"16","target":"17"},
{"source":"17","target":"14"},
{"source":"17","target":"16"},
{"source":"18","target":"12"},
{"source":"18","target":"19"},
{"source":"18","target":"29"},
{"source":"18","target":"40"},
{"source":"18","target":"46"},
{"source":"18","target":"51"},
{"source":"18","target":"58"},
{"source":"18","target":"60"},
{"source":"18","target":"82"},
{"source":"19","target":"18"},
{"source":"20","target":"49"},
{"source":"20","target":"66"},
{"source":"21","target":"7"},
{"source":"22","target":"28"},
{"source":"22","target":"75"},
{"source":"23","target":"41"},
{"source":"24","target":"41"},
{"source":"25","target":"10"},
{"source":"26","target":"61"},
{"source":"27","target":"64"},
{"source":"28","target":"62"},
{"source":"28","target":"22"},
{"source":"28","target":"32"},
{"source":"29","target":"18"},
{"source":"30","target":"56"},
{"source":"30","target":"36"},
{"source":"31","target":"63"},
{"source":"32","target":"28"},
{"source":"32","target":"75"},
{"source":"33","target":"57"},
{"source":"34","target":"35"},
{"source":"37","target":"35"},
{"source":"35","target":"34"},
{"source":"35","target":"37"},
{"source":"36","target":"46"},
{"source":"36","target":"47"},
{"source":"36","target":"30"},
{"source":"38","target":"64"},
{"source":"38","target":"39"},
{"source":"39","target":"38"},
{"source":"40","target":"18"},
{"source":"41","target":"23"},
{"source":"41","target":"24"},
{"source":"42","target":"83"},
{"source":"43","target":"52"},
{"source":"44","target":"25"},
{"source":"45","target":"61"},
{"source":"46","target":"18"},
{"source":"46","target":"36"},
{"source":"47","target":"36"},
{"source":"47","target":"56"},
{"source":"47","target":"49"},
{"source":"48","target":"4"},
{"source":"49","target":"61"},
{"source":"49","target":"47"},
{"source":"49","target":"20"},
{"source":"49","target":"66"},
{"source":"49","target":"77"},
{"source":"50","target":"61"},
{"source":"51","target":"18"},
{"source":"52","target":"43"},
{"source":"52","target":"6"},
{"source":"53","target":"61"},
{"source":"54","target":"5"},
{"source":"55","target":"68"},
{"source":"56","target":"9"},
{"source":"56","target":"30"},
{"source":"56","target":"47"},
{"source":"57","target":"64"},
{"source":"57","target":"61"},
{"source":"57","target":"83"},
{"source":"57","target":"3"},
{"source":"57","target":"33"},
{"source":"58","target":"18"},
{"source":"59","target":"61"},
{"source":"60","target":"18"},
{"source":"61","target":"64"},
{"source":"61","target":"83"},
{"source":"61","target":"57"},
{"source":"61","target":"3"},
{"source":"61","target":"26"},
{"source":"61","target":"45"},
{"source":"61","target":"49"},
{"source":"61","target":"50"},
{"source":"61","target":"53"},
{"source":"61","target":"59"},
{"source":"61","target":"76"},
{"source":"61","target":"81"},
{"source":"62","target":"11"},
{"source":"62","target":"28"},
{"source":"62","target":"75"},
{"source":"63","target":"31"},
{"source":"64","target":"61"},
{"source":"64","target":"83"},
{"source":"64","target":"57"},
{"source":"64","target":"3"},
{"source":"64","target":"8"},
{"source":"64","target":"13"},
{"source":"64","target":"27"},
{"source":"64","target":"38"},
{"source":"64","target":"74"},
{"source":"65","target":"83"},
{"source":"66","target":"49"},
{"source":"66","target":"20"},
{"source":"67","target":"72"},
{"source":"68","target":"55"},
{"source":"69","target":"3"},
{"source":"70","target":"3"},
{"source":"71","target":"3"},
{"source":"72","target":"67"},
{"source":"73","target":"74"},
{"source":"74","target":"64"},
{"source":"74","target":"73"},
{"source":"75","target":"62"},
{"source":"75","target":"22"},
{"source":"75","target":"32"},
{"source":"76","target":"61"},
{"source":"77","target":"49"},
{"source":"78","target":"7"},
{"source":"79","target":"80"},
{"source":"80","target":"79"},
{"source":"81","target":"61"},
{"source":"82","target":"18"},
{"source":"83","target":"64"},
{"source":"83","target":"61"},
{"source":"83","target":"42"},
{"source":"83","target":"14"},
{"source":"83","target":"3"},
{"source":"83","target":"57"},
{"source":"83","target":"65"},
{"source":"25","target":"44"}
],
    "categories": [
      {
        "name": "Tang Monk's team"
      },
      {
        "name": "gods/Buddhas"
      },
      {
        "name": "humans"
      },
      {
        "name": "monsters"
      }
    ]
  }