{"nodes": [
      {"name": "白骨精"},
      {"name": "白鹿精"},
      {"name": "白面狐狸"},
      {"name": "白象精(二魔)"},
      {"name": "白衣秀士"},
      {"name": "百眼魔君"},
      {"name": "辟尘大王(犀牛精)"},
      {"name": "辟寒大王(犀牛精)"},
      {"name": "辟暑大王(犀牛精)"},
      {"name": "独角兕大王"},
      {"name": "拂云叟"},
      {"name": "孤直公"},
      {"name": "黑熊精"},
      {"name": "红孩儿"},
      {"name": "红麟大蟒"},
      {"name": "狐阿七大王"},
      {"name": "虎力大仙"},
      {"name": "黄风怪"},
      {"name": "黄眉大王"},
      {"name": "黄袍怪"},
      {"name": "黄狮精"},
      {"name": "混世魔王"},
      {"name": "金鼻白毛老鼠精"},
      {"name": "金翅大鹏(三魔)"},
      {"name": "金角大王"},
      {"name": "劲节十八公"},
      {"name": "九灵元圣"},
      {"name": "九头虫"},
      {"name": "灵感大王(鲤鱼精)"},
      {"name": "凌空子"},
      {"name": "凌虚子"},
      {"name": "六耳猕猴"},
      {"name": "鹿力大仙"},
      {"name": "南山大王"},
      {"name": "牛魔王"},
      {"name": "青狮精(大魔)"},
      {"name": "如意真仙"},
      {"name": "赛太岁"},
      {"name": "狮俐王"},
      {"name": "特处士"},
      {"name": "铁扇公主"},
      {"name": "鼍洁"},
      {"name": "万圣公主"},
      {"name": "万圣龙王"},
      {"name": "蝎子精"},
      {"name": "杏仙"},
      {"name": "熊山君"},
      {"name": "压龙洞九尾狐干妈"},
      {"name": "羊力大仙"},
      {"name": "寅将军"},
      {"name": "银角大王"},
      {"name": "玉面公主"},
      {"name": "玉兔精"},
      {"name": "蜘蛛七精"},
      {"name": "宠物下凡"},
      {"name": "道家背景"},
      {"name": "灵山背景"},
      {"name": "神仙背景"},
      {"name": "无背景"},
      {"name": "坐骑下凡"},
      {"name": "雄性"},
      {"name": "雌性"},
      {"name": "活"},
      {"name": "死"}
   ],
   "links": [
      {"source":"白骨精","target":"无背景","value":1},
{"source":"白鹿精","target":"坐骑下凡","value":1},
{"source":"白面狐狸","target":"无背景","value":1},
{"source":"白象精(二魔)","target":"灵山背景","value":1},
{"source":"白衣秀士","target":"无背景","value":1},
{"source":"百眼魔君","target":"无背景","value":1},
{"source":"辟尘大王(犀牛精)","target":"无背景","value":1},
{"source":"辟寒大王(犀牛精)","target":"无背景","value":1},
{"source":"辟暑大王(犀牛精)","target":"无背景","value":1},
{"source":"独角兕大王","target":"道家背景","value":1},
{"source":"拂云叟","target":"无背景","value":1},
{"source":"孤直公","target":"无背景","value":1},
{"source":"黑熊精","target":"无背景","value":1},
{"source":"红孩儿","target":"无背景","value":1},
{"source":"红麟大蟒","target":"无背景","value":1},
{"source":"狐阿七大王","target":"无背景","value":1},
{"source":"虎力大仙","target":"无背景","value":1},
{"source":"黄风怪","target":"灵山背景","value":1},
{"source":"黄眉大王","target":"灵山背景","value":1},
{"source":"黄袍怪","target":"神仙背景","value":1},
{"source":"黄狮精","target":"无背景","value":1},
{"source":"混世魔王","target":"无背景","value":1},
{"source":"金鼻白毛老鼠精","target":"灵山背景","value":1},
{"source":"金翅大鹏(三魔)","target":"灵山背景","value":1},
{"source":"金角大王","target":"道家背景","value":1},
{"source":"劲节十八公","target":"无背景","value":1},
{"source":"九灵元圣","target":"坐骑下凡","value":1},
{"source":"九头虫","target":"无背景","value":1},
{"source":"灵感大王(鲤鱼精)","target":"灵山背景","value":1},
{"source":"凌空子","target":"无背景","value":1},
{"source":"凌虚子","target":"无背景","value":1},
{"source":"六耳猕猴","target":"无背景","value":1},
{"source":"鹿力大仙","target":"无背景","value":1},
{"source":"南山大王","target":"无背景","value":1},
{"source":"牛魔王","target":"无背景","value":1},
{"source":"青狮精(大魔)","target":"灵山背景","value":1},
{"source":"如意真仙","target":"无背景","value":1},
{"source":"赛太岁","target":"灵山背景","value":1},
{"source":"狮俐王","target":"灵山背景","value":1},
{"source":"特处士","target":"无背景","value":1},
{"source":"铁扇公主","target":"无背景","value":1},
{"source":"鼍洁","target":"神仙背景","value":1},
{"source":"万圣公主","target":"无背景","value":1},
{"source":"万圣龙王","target":"无背景","value":1},
{"source":"蝎子精","target":"灵山背景","value":1},
{"source":"杏仙","target":"无背景","value":1},
{"source":"熊山君","target":"无背景","value":1},
{"source":"压龙洞九尾狐干妈","target":"无背景","value":1},
{"source":"羊力大仙","target":"无背景","value":1},
{"source":"寅将军","target":"无背景","value":1},
{"source":"银角大王","target":"道家背景","value":1},
{"source":"玉面公主","target":"无背景","value":1},
{"source":"玉兔精","target":"宠物下凡","value":1},
{"source":"蜘蛛七精","target":"无背景","value":1},
{"source":"宠物下凡","target":"雌性","value":1},
{"source":"道家背景","target":"雄性","value":3},
{"source":"灵山背景","target":"雄性","value":8},
{"source":"灵山背景","target":"雌性","value":2},
{"source":"神仙背景","target":"雄性","value":2},
{"source":"无背景","target":"雄性","value":28},
{"source":"无背景","target":"雌性","value":8},
{"source":"坐骑下凡","target":"雄性","value":2},
{"source":"雌性","target":"活","value":4},
{"source":"雌性","target":"死","value":7},
{"source":"雄性","target":"活","value":22},
{"source":"雄性","target":"死","value":21}
   ]}
